[
  "**** Error\tMon Mar 07 12:53:42 GMT 2016\t1457355222637\t/atg/cloud/rest/JerseyServicesManager\tclientSideErrors[0] : {\"message\":\"Uncaught Error: Script error for: //server1.company.com/EEAdmin/js/ee/js/atgsvcs-test.js\\nhttp://requirejs.org/docs/errors.html#scripterror\",\"time\":\"2016-03-07T12:53:42.615Z\",\"browserVersion\":\"Chrome 48.0.2564.116\",\"osVersion\":\"Win32\",\"locale\":\"en-US\",\"visitorId\":null,\"line\":8,\"visitId\":null,\"clientErrorCode\":\"15006\",\"url\":\"http://localhost:8080/shared/js/libs/oraclejet/libs/require/require.js\"}",
  "**** Error\tMon Mar 07 12:54:36 GMT 2016\t1457355276007\t/atg/cloud/rest/JerseyServicesManager\tclientSideErrors[0] : {\"message\":\"Script error for: //server1.company.com/EEAdmin/js/ee/js/atgsvcs-test.js\\nhttp://requirejs.org/docs/errors.html#scripterror\",\"time\":\"2016-03-07T12:54:35.756Z\",\"browserVersion\":\"Chrome 42.0.2311.135\",\"osVersion\":\"Win32\",\"locale\":\"en-US\",\"visitorId\":null,\"line\":8,\"visitId\":null,\"clientErrorCode\":\"15007\",\"url\":\"http://10.0.2.2:8080/shared/js/libs/oraclejet/libs/require/require.js\"}",
  "**** Error\tMon Mar 07 12:54:41 GMT 2016\t1457355281165\t/atg/cloud/rest/JerseyServicesManager\tclientSideErrors[0] : {\"message\":\"Script error for: //server1.company.com/EEAdmin/js/ee/js/atgsvcs-test.js\\nhttp://requirejs.org/docs/errors.html#scripterror\",\"time\":\"2016-03-07T12:54:40.514Z\",\"browserVersion\":\"Chrome 42.0.2311.135\",\"osVersion\":\"Win32\",\"locale\":\"en-US\",\"visitorId\":null,\"line\":8,\"visitId\":null,\"clientErrorCode\":\"15007\",\"url\":\"http://10.0.2.2:8080/shared/js/libs/oraclejet/libs/require/require.js\"}",
  "**** Error\tMon Mar 07 12:55:05 GMT 2016\t1457355305773\t/atg/cloud/rest/JerseyServicesManager\tclientSideErrors[0] : {\"message\":\"Script error for: //server1.company.com/EEAdmin/js/ee/js/atgsvcs-test.js\\nhttp://requirejs.org/docs/errors.html#scripterror\",\"time\":\"2016-03-07T12:55:05.169Z\",\"browserVersion\":\"Chrome 42.0.2311.135\",\"osVersion\":\"Win32\",\"locale\":\"en-US\",\"visitorId\":null,\"line\":8,\"visitId\":null,\"clientErrorCode\":\"15007\",\"url\":\"http://10.0.2.2:8080/shared/js/libs/oraclejet/libs/require/require.js\"}",
  "**** Error\tMon Mar 07 12:55:29 GMT 2016\t1457355329312\t/atg/cloud/rest/JerseyServicesManager\tclientSideErrors[0] : {\"message\":\"Script error for: //server1.company.com/EEAdmin/js/ee/js/atgsvcs-test.js\\nhttp://requirejs.org/docs/errors.html#scripterror\",\"time\":\"2016-03-07T12:55:29.221Z\",\"browserVersion\":\"Chrome 42.0.2311.135\",\"osVersion\":\"Win32\",\"locale\":\"en-US\",\"visitorId\":null,\"line\":8,\"visitId\":null,\"clientErrorCode\":\"15007\",\"url\":\"http://10.0.2.2:8080/shared/js/libs/oraclejet/libs/require/require.js\"}",
  "**** Error\tFri Apr 22 17:18:40 BST 2016\t1461341920314\t/atg/cloud/rest/JerseyServicesManager\tclientSideErrors[0] : {\"message\":\"Uncaught Error: Script error for: //server1.company.com/EEAdmin/js/ee/js/cc-metrics-1.0.js\\nhttp://requirejs.org/docs/errors.html#scripterror\",\"time\":\"2016-04-22T16:18:40.299Z\",\"browserVersion\":\"Chrome 49.0.2623.112\",\"osVersion\":\"Win32\",\"locale\":\"en-US\",\"visitorId\":null,\"line\":8,\"visitId\":null,\"clientErrorCode\":\"15006\",\"url\":\"http://localhost:8080/shared/js/libs/oraclejet/libs/require/require.js\"}",
  "**** Error\tFri Apr 22 17:21:38 BST 2016\t1461342098896\t/atg/cloud/rest/JerseyServicesManager\tclientSideErrors[0] : {\"message\":\"Uncaught Error: Script error for: //server1.company.com/EEAdmin/js/ee/js/cc-metrics-1.0.js\\nhttp://requirejs.org/docs/errors.html#scripterror\",\"time\":\"2016-04-22T16:21:38.883Z\",\"browserVersion\":\"Chrome 49.0.2623.112\",\"osVersion\":\"Win32\",\"locale\":\"en-US\",\"visitorId\":null,\"line\":8,\"visitId\":null,\"clientErrorCode\":\"15006\",\"url\":\"http://localhost:8080/shared/js/libs/oraclejet/libs/require/require.js\"}",
  "**** Error\tFri Apr 22 17:26:19 BST 2016\t1461342379671\t/atg/cloud/rest/JerseyServicesManager\tclientSideErrors[0] : {\"message\":\"Uncaught Error: Script error for: //server1.company.com/EEAdmin/js/ee/js/cc-metrics-1.0.js\\nhttp://requirejs.org/docs/errors.html#scripterror\",\"time\":\"2016-04-22T16:26:19.651Z\",\"browserVersion\":\"Chrome 49.0.2623.112\",\"osVersion\":\"Win32\",\"locale\":\"en-US\",\"visitorId\":null,\"line\":8,\"visitId\":null,\"clientErrorCode\":\"15006\",\"url\":\"http://localhost:8080/shared/js/libs/oraclejet/libs/require/require.js\"}",
  "**** Error\tFri Apr 22 17:32:27 BST 2016\t1461342747801\t/atg/cloud/rest/JerseyServicesManager\tclientSideErrors[0] : {\"message\":\"Uncaught Error: Script error for: //server1.company.com/EEAdmin/js/ee/js/cc-metrics-1.0.js\\nhttp://requirejs.org/docs/errors.html#scripterror\",\"time\":\"2016-04-22T16:32:27.787Z\",\"browserVersion\":\"Chrome 49.0.2623.112\",\"osVersion\":\"Win32\",\"locale\":\"en-US\",\"visitorId\":null,\"line\":8,\"visitId\":null,\"clientErrorCode\":\"15006\",\"url\":\"http://localhost:8080/shared/js/libs/oraclejet/libs/require/require.js\"}",
  "**** Error\tTue May 24 10:21:21 UTC 2016\t1464085281656\t/atg/cloud/rest/JerseyServicesManager\tclientSideErrors[0] : {\"message\":\"Uncaught Error: Script error for: //server1.company.com/EEAdmin/js/ee/js/cc-metrics-1.0.js\\nhttp://requirejs.org/docs/errors.html#scripterror\",\"time\":\"2016-05-24T10:21:21.154Z\",\"browserVersion\":\"Chrome 50.0.2661.102\",\"osVersion\":\"Win32\",\"locale\":\"en-US\",\"visitorId\":null,\"line\":8,\"visitId\":null,\"clientErrorCode\":\"15006\",\"url\":\"http://localhost:8080/shared/js/libs/oraclejet/libs/require/require.js\"}",
  "**** Error\tTue May 24 10:22:19 UTC 2016\t1464085339970\t/atg/cloud/rest/JerseyServicesManager\tclientSideErrors[0] : {\"message\":\"Uncaught Error: Script error for: //server1.company.com/EEAdmin/js/ee/js/cc-metrics-1.0.js\\nhttp://requirejs.org/docs/errors.html#scripterror\",\"time\":\"2016-05-24T10:22:19.937Z\",\"browserVersion\":\"Chrome 50.0.2661.102\",\"osVersion\":\"Win32\",\"locale\":\"en-US\",\"visitorId\":null,\"line\":8,\"visitId\":null,\"clientErrorCode\":\"15006\",\"url\":\"http://localhost:8080/shared/js/libs/oraclejet/libs/require/require.js\"}",
  "**** Error\tTue May 24 10:22:25 UTC 2016\t1464085345538\t/atg/cloud/rest/JerseyServicesManager\tclientSideErrors[0] : {\"message\":\"Uncaught Error: Script error for: //server1.company.com/EEAdmin/js/ee/js/cc-metrics-1.0.js\\nhttp://requirejs.org/docs/errors.html#scripterror\",\"time\":\"2016-05-24T10:22:25.519Z\",\"browserVersion\":\"Chrome 50.0.2661.102\",\"osVersion\":\"Win32\",\"locale\":\"en-US\",\"visitorId\":null,\"line\":8,\"visitId\":null,\"clientErrorCode\":\"15006\",\"url\":\"http://localhost:8080/shared/js/libs/oraclejet/libs/require/require.js\"}",
  "**** Error\tWed Aug 17 11:55:39 UTC 2016\t1471434939791\t/atg/cloud/rest/JerseyServicesManager\tclientSideErrors[0] : {\"message\":\"Uncaught Error: Script error for: //server1.company.com/EEAdmin/js/ee/js/cc-metrics-1.0.js\\nhttp://requirejs.org/docs/errors.html#scripterror\",\"time\":\"2016-08-17T11:55:39.764Z\",\"browserVersion\":\"Chrome 52.0.2743.116\",\"osVersion\":\"Win32\",\"locale\":\"en-US\",\"visitorId\":\"1298cUU_UfsMSIC45QGPpM9wo2-NQAJPna9bnlFpYkXRxSs661E\",\"line\":8,\"visitId\":\"-14ddf4e9:156217da656:-35ae-123.456.789.100\",\"clientErrorCode\":\"15006\",\"url\":\"http://localhost:8080/js/oraclejet/js/libs/require/require.js\"}",
  "**** Error\tWed Aug 17 12:02:03 UTC 2016\t1471435323630\t/atg/cloud/rest/JerseyServicesManager\tclientSideErrors[0] : {\"message\":\"Uncaught Error: Script error for: //server1.company.com/EEAdmin/js/ee/js/cc-metrics-1.0.js\\nhttp://requirejs.org/docs/errors.html#scripterror\",\"time\":\"2016-08-17T12:02:03.581Z\",\"browserVersion\":\"Chrome 52.0.2743.116\",\"osVersion\":\"Win32\",\"locale\":\"en-US\",\"visitorId\":\"1298cUU_UfsMSIC45QGPpM9wo2-NQAJPna9bnlFpYkXRxSs661E\",\"line\":8,\"visitId\":\"-14ddf4e9:156217da656:-35ae-123.456.789.100\",\"clientErrorCode\":\"15006\",\"url\":\"http://localhost:8080/js/oraclejet/js/libs/require/require.js\"}",
  "**** Error\tThu Aug 18 10:43:34 UTC 2016\t1471517014548\t/atg/cloud/rest/JerseyServicesManager\tclientSideErrors[0] : {\"message\":\"Uncaught Error: Script error for: //server1.company.com/EEAdmin/js/ee/js/cc-metrics-1.0.js\\nhttp://requirejs.org/docs/errors.html#scripterror\",\"time\":\"2016-08-18T10:43:34.483Z\",\"browserVersion\":\"Chrome 52.0.2743.116\",\"osVersion\":\"Win32\",\"locale\":\"en-US\",\"visitorId\":\"1298cUU_UfsMSIC45QGPpM9wo2-NQAJPna9bnlFpYkXRxSs661E\",\"line\":8,\"visitId\":\"-14ddf4e9:156217da656:-35ae-123.456.789.100\",\"clientErrorCode\":\"15006\",\"url\":\"http://localhost:8080/js/oraclejet/js/libs/require/require.js\"}",
  "**** Error\tThu Aug 18 10:43:42 UTC 2016\t1471517022812\t/atg/cloud/rest/JerseyServicesManager\tclientSideErrors[0] : {\"message\":\"Uncaught Error: Script error for: //server1.company.com/EEAdmin/js/ee/js/cc-metrics-1.0.js\\nhttp://requirejs.org/docs/errors.html#scripterror\",\"time\":\"2016-08-18T10:43:42.779Z\",\"browserVersion\":\"Chrome 52.0.2743.116\",\"osVersion\":\"Win32\",\"locale\":\"en-US\",\"visitorId\":\"1298cUU_UfsMSIC45QGPpM9wo2-NQAJPna9bnlFpYkXRxSs661E\",\"line\":8,\"visitId\":\"-14ddf4e9:156217da656:-2bb6-123.456.789.100\",\"clientErrorCode\":\"15006\",\"url\":\"http://localhost:8080/js/oraclejet/js/libs/require/require.js\"}",
  "**** Error\tThu Aug 18 14:34:50 UTC 2016\t1471530890273\t/atg/cloud/rest/JerseyServicesManager\tclientSideErrors[0] : {\"message\":\"Uncaught Error: Script error for: //server1.company.com/EEAdmin/js/ee/js/cc-metrics-1.0.js\\nhttp://requirejs.org/docs/errors.html#scripterror\",\"time\":\"2016-08-18T14:34:50.248Z\",\"browserVersion\":\"Chrome 52.0.2743.116\",\"osVersion\":\"Win32\",\"locale\":\"en-US\",\"visitorId\":\"1298cUU_UfsMSIC45QGPpM9wo2-NQAJPna9bnlFpYkXRxSs661E\",\"line\":8,\"visitId\":\"-14ddf4e9:156217da656:-2bb6-123.456.789.100\",\"clientErrorCode\":\"15006\",\"url\":\"http://localhost:8080/js/oraclejet/js/libs/require/require.js\"}",
  "**** Error\tThu Aug 18 14:54:13 UTC 2016\t1471532053252\t/atg/cloud/rest/JerseyServicesManager\tclientSideErrors[0] : {\"message\":\"Uncaught Error: Script error for: //server1.company.com/EEAdmin/js/ee/js/cc-metrics-1.0.js\\nhttp://requirejs.org/docs/errors.html#scripterror\",\"time\":\"2016-08-18T14:54:13.175Z\",\"browserVersion\":\"Chrome 52.0.2743.116\",\"osVersion\":\"Win32\",\"locale\":\"en-US\",\"visitorId\":\"1298cUU_UfsMSIC45QGPpM9wo2-NQAJPna9bnlFpYkXRxSs661E\",\"line\":8,\"visitId\":\"-14ddf4e9:156217da656:-2bb6-123.456.789.100\",\"clientErrorCode\":\"15006\",\"url\":\"http://localhost:8080/js/oraclejet/js/libs/require/require.js\"}",
  "**** Error\tMon Sep 19 09:35:49 UTC 2016\t1474277749004\t/atg/cloud/rest/JerseyServicesManager\tclientSideErrors[0] : {\"clientErrorCode\":\"15006\",\"osVersion\":\"Win32\",\"visitId\":\"-14ddf4e9:156217da656:-2bb6-123.456.789.100\",\"line\":8,\"browserVersion\":\"Chrome 53.0.2785.116\",\"time\":\"2016-09-19T09:35:48.900Z\",\"message\":\"Uncaught Error: Script error for: //server1.company.com/EEAdmin/js/ee/js/atgsvcs-test.js\\nhttp://requirejs.org/docs/errors.html#scripterror\",\"locale\":\"en-US\",\"url\":\"http://localhost:8080/js/oraclejet/js/libs/require/require.js\",\"visitorId\":\"1298cUU_UfsMSIC45QGPpM9wo2-NQAJPna9bnlFpYkXRxSs661E\"}"
]