{
  "properties": {
    "eligibleForProductWithSurcharges": {
      "description": "whether this shipping method is enabled for products with surcharges or not.",
      "type": "boolean"
    },
    "shippingCalculator": {
      "description": "A valid key for the available calculator types.",
      "type": "string"
    },
    "isExternallyPriced": {
      "description": "Whether this shipping method can be priced externally or not. Defaults to false.",
      "type": "boolean"
    },
    "ranges": {
      "description": "The price ranges for this shipping method.",
      "type": "array",
      "items": {
        "type": "object",
        "properties": {
          "high": {
            "description": "The upper boundary of the range.",
            "type": "number"
          },
          "amount": {
            "description": "The value for the range in selected price list group.",
            "type": "number"
          },
          "secondaryCurrencyShippingAmount": {
            "description": "The value for the range in monetary currency. In case of mix currency, if payShippingInSecondaryCurrency flag is set to true and the secondaryCurrencyCode is set at site, this amount will be calculated according to the exchange rate defined between selected priceListGroup's currency code and site's secondary currency code",
            "type": "number"
          },
          "low": {
            "description": "The lower boundary of the range.",
            "type": "number"
          },
          "repositoryId": {
            "description": "The repository id of this priceRange item.",
            "type": "string"
          }
        }
      }
    },
    "displayName": {
      "description": "The display name for the shipping method given the current locale.",
      "type": "string"
    },
    "description": {
      "description": "Description of the shipping method.",
      "type": "string"
    },
    "type": {
      "description": "The type property of the shipping method.",
      "type": "integer"
    },
    "taxCode": {
      "description": "A valid tax code for calculating tax on shipping.",
      "type": "string"
    },
    "shippingGroupType": {
      "description": "Shipping group type.",
      "type": "string"
    },
    "enabled": {
      "description": "whether this shipping method is enabled or not.",
      "type": "boolean"
    },
    "displaySequence": {
      "description": "Used to determine the ordering of shipping methods in the UI. Lower values should appear first in any ordered list.",
      "type": "integer"
    },
    "repositoryId": {
      "description": "the id of the newly created shipping method item",
      "type": "string"
    },
    "isFallback": {
      "description": "Use this shipping method when Commerce Cloud cannot connect to an external shipping service. Defaults to false.",
      "type": "boolean"
    },
    "shipToLocations": {
      "description": "List of shipping locations",
      "type": "array",
      "items": {
        "type": "object",
        "properties": {
          "repositoryId": {
            "description": "Allowed shipping country-region IDs.",
            "type": "string"
          }
        }
      }
    }
  }
}