{
  "properties": {
    "shippingGroups": {
      "description": "The shipping groups for the order.",
      "type": "array",
      "items": {
        "type": "object",
        "properties": {
          "surcharge": {
            "description": "The shipping surcharge.",
            "type": "number"
          },
          "priceInfo": {
            "description": "The price information.",
            "type": "object",
            "properties": {
              "secondaryCurrencyTaxAmount": {
                "description": "The current  total tax amount in monetry currency",
                "type": "number"
              },
              "amount": {
                "description": "The total order amount.",
                "type": "number"
              },
              "total": {
                "description": "The order total.",
                "type": "number"
              },
              "secondaryCurrencyShippingAmount": {
                "description": "The current  total shipping amount in monetry currency ",
                "type": "number"
              },
              "shipping": {
                "description": "The total shipping cost.",
                "type": "number"
              },
              "primaryCurrencyTotal": {
                "description": "The current total in loyalty points in case of multi currency",
                "type": "number"
              },
              "secondaryCurrencyTotal": {
                "description": "The current  total (sum of shipping and tax)amount in monetry currency",
                "type": "number"
              },
              "secondaryCurrencyShippingSurchargeValue": {
                "description": "Extra handling costs for shipping the products in monetry currency.",
                "type": "number"
              },
              "shippingSurchargeValue": {
                "description": "Extra handling costs for shipping the products.",
                "type": "number"
              },
              "tax": {
                "description": "The total tax amount.",
                "type": "number"
              },
              "subTotal": {
                "description": "Sub-total.",
                "type": "number"
              },
              "currencyCode": {
                "description": "The currency code.",
                "type": "string"
              }
            }
          },
          "recurringChargePriceInfo": {
            "description": "Recurring charge price information.",
            "type": "object",
            "properties": {
              "amount": {
                "description": "The monetary amount of this recurring charge.",
                "type": "number"
              },
              "total": {
                "description": "The total price of the recurring charge.",
                "type": "number"
              },
              "frequencyAmountTotals": {
                "description": "The total for each recurring charge frequency",
                "type": "array",
                "items": {
                  "type": "object",
                  "properties": {
                    "total": {
                      "description": "The total amount for the frequency.",
                      "type": "string"
                    },
                    "frequency": {
                      "description": "The frequency for the item's total e.g. Monthly.",
                      "type": "string"
                    }
                  }
                }
              },
              "shipping": {
                "description": "Cost of shipping the product.",
                "type": "number"
              },
              "tax": {
                "description": "Monetary tax amount.",
                "type": "number"
              },
              "subTotal": {
                "description": "The sub-total price of the recurring charge.",
                "type": "number"
              },
              "frequencyTaxTotals": {
                "description": "The tax for each recurring charge frequency",
                "type": "array",
                "items": {
                  "type": "object",
                  "properties": {
                    "tax": {
                      "description": "The tax amount for the frequency.",
                      "type": "string"
                    },
                    "frequency": {
                      "description": "The frequency for the item's tax e.g. Monthly.",
                      "type": "string"
                    }
                  }
                }
              },
              "currencyCode": {
                "description": "The currency code for the monetary amounts. A three character currency code such as USD.",
                "type": "string"
              },
              "totalWithoutTax": {
                "description": "Total of recurring amount without tax included.",
                "type": "number"
              }
            }
          },
          "trackingInfo": {
            "description": "Tracking Information for the Order.",
            "type": "array",
            "items": {
              "type": "object",
              "properties": {
                "carrierName": {
                  "description": "Carrier Name for Tracking.",
                  "type": "string"
                },
                "carrierUrl": {
                  "description": "Carrier URL for Tracking.",
                  "type": "string"
                },
                "carrierId": {
                  "description": "Carrier Id for Tracking.",
                  "type": "string"
                },
                "trackingNumber": {
                  "description": "Tracking Number.",
                  "type": "string"
                }
              }
            }
          },
          "shippingMethod": {
            "description": "The shipping method details for the order.",
            "type": "object",
            "properties": {
              "secondaryCurrencyTaxAmount": {
                "description": "Shipping tax amount in monetry currency",
                "type": "number"
              },
              "shippingTax": {
                "description": "The shipping tax.",
                "type": "number"
              },
              "cost": {
                "description": "The total cost of shipping.",
                "type": "number"
              },
              "secondaryCurrencyShipingAmount": {
                "description": "shipping amount in monetry currency ",
                "type": "number"
              },
              "value": {
                "description": "The shipping method applied to the order.",
                "type": "string"
              },
              "shippingMethodDescription": {
                "description": "The description of the shipping method.",
                "type": "string"
              }
            }
          },
          "shippingAddress": {
            "description": "The shipping address details.",
            "type": "object",
            "properties": {
              "lastName": {
                "description": "Last name.",
                "type": "string"
              },
              "country": {
                "description": "Country.",
                "type": "string"
              },
              "address3": {
                "description": "Address snippet.",
                "type": "string"
              },
              "address2": {
                "description": "Address snippet.",
                "type": "string"
              },
              "city": {
                "description": "City.",
                "type": "string"
              },
              "prefix": {
                "description": "Name prefix.",
                "type": "string"
              },
              "address1": {
                "description": "Address snippet.",
                "type": "string"
              },
              "postalCode": {
                "description": "Postal code.",
                "type": "string"
              },
              "jobTitle": {
                "description": "Job title.",
                "type": "string"
              },
              "companyName": {
                "description": "Company name.",
                "type": "string"
              },
              "county": {
                "description": "County.",
                "type": "string"
              },
              "suffix": {
                "description": "Name suffix.",
                "type": "string"
              },
              "selectedCountry": {
                "description": "Country code.",
                "type": "string"
              },
              "firstName": {
                "description": "First name",
                "type": "string"
              },
              "phoneNumber": {
                "description": "Phone number.",
                "type": "string"
              },
              "alias": {
                "description": "Address alias.",
                "type": "string"
              },
              "faxNumber": {
                "description": "Fax number.",
                "type": "string"
              },
              "middleName": {
                "description": "Middle name.",
                "type": "string"
              },
              "state": {
                "description": "State.",
                "type": "string"
              },
              "selectedState": {
                "description": "State code.",
                "type": "string"
              },
              "email": {
                "description": "Email address.",
                "type": "string"
              },
              "state_ISOCode": {
                "description": "State ISO code.",
                "type": "string"
              }
            }
          },
          "trackingNumber": {
            "description": "The tracking number.",
            "type": "string"
          },
          "items": {
            "description": "The array of products in the shipping group.",
            "type": "array",
            "items": {
              "type": "object",
              "properties": {
                "deactivationDate": {
                  "description": "The deactivation date in ISO format.",
                  "type": "string"
                },
                "rawTotalPrice": {
                  "description": "The raw price of the product.",
                  "type": "integer"
                },
                "displayName": {
                  "description": "The name of the product.",
                  "type": "string"
                },
                "dynamicProperties": {
                  "description": "Array of custom properties at order line item level.",
                  "type": "array",
                  "items": {
                    "type": "object",
                    "properties": {
                      "id": {
                        "description": "The ID of the dynamic property.",
                        "type": "string"
                      },
                      "label": {
                        "description": "The label of the dynamic property.",
                        "type": "string"
                      },
                      "value": {
                        "description": "The value of the dynamic property.",
                        "type": "string"
                      }
                    }
                  }
                },
                "externalData": {
                  "description": "External data to be associated with a commerce item, provided by a configurator system.",
                  "type": "array",
                  "items": {
                    "type": "object",
                    "properties": {
                      "values": {
                        "description": "The array of values associated with an externalData item.",
                        "type": "object",
                        "properties": {
                          "dynamic_property_key": {
                            "description": "This property's name and value will be retrieved from a configurator system, so will be dynamically set.",
                            "type": "string"
                          }
                        }
                      },
                      "name": {
                        "description": "The name to be associated with the externalData item.",
                        "type": "string"
                      },
                      "actionCode": {
                        "description": "The action code that has been set on the externalData item by the configurator system.",
                        "type": "string"
                      }
                    }
                  }
                },
                "billingAccountId": {
                  "description": "The billing account ID associated to the current item.",
                  "type": "string"
                },
                "assetId": {
                  "description": "The asset ID corresponding to the current item.",
                  "type": "string"
                },
                "price": {
                  "description": "The actual price of the product.",
                  "type": "integer"
                },
                "variant": {
                  "description": "List of variants for the product.",
                  "type": "array",
                  "items": {
                    "type": "object",
                    "properties": {
                      "optionValue": {
                        "description": "The variant option value.",
                        "type": "string"
                      },
                      "optionName": {
                        "description": "The variant option name.",
                        "type": "string"
                      }
                    }
                  }
                },
                "actionCode": {
                  "description": "The action code that has been set on the item by the configurator system.",
                  "type": "string"
                },
                "serviceId": {
                  "description": "The service ID associated to the current item.",
                  "type": "string"
                },
                "unitPrice": {
                  "description": "The unit price of the product.",
                  "type": "integer"
                },
                "serviceAccountId": {
                  "description": "The service account ID associated to the current item.",
                  "type": "string"
                },
                "quantity": {
                  "description": "The quantity of the product in the shipping group.",
                  "type": "integer"
                },
                "productId": {
                  "description": "ID of the product in the cart.",
                  "type": "string"
                },
                "externalRecurringCharge": {
                  "description": "The external recurring price.",
                  "type": "number"
                },
                "active": {
                  "description": "active or not.",
                  "type": "boolean"
                },
                "externalRecurringChargeFrequency": {
                  "description": "The frequency for the recurring charge e.g. Monthly.",
                  "type": "string"
                },
                "catRefId": {
                  "description": "The category to which the product belongs.",
                  "type": "string"
                },
                "externalRecurringChargeDuration": {
                  "description": "The duration for the recurring charge e.g. 12 months.",
                  "type": "string"
                },
                "skuProperties": {
                  "description": "Sku properties Information",
                  "type": "array",
                  "items": {
                    "type": "object",
                    "properties": {
                      "propertyType": {
                        "description": "Type that indicates whether it is a base or a custom SKU property,",
                        "type": "string"
                      },
                      "name": {
                        "description": "Name of the Dynamic SKU Property.",
                        "type": "string"
                      },
                      "id": {
                        "description": "ID of the Dynamic SKU Property.",
                        "type": "string"
                      },
                      "value": {
                        "description": "Value of the Dynamic SKU Property.",
                        "type": "string"
                      }
                    }
                  }
                },
                "customerAccountId": {
                  "description": "The customer account ID associated to the current item.",
                  "type": "string"
                },
                "discountInfo": {
                  "description": "The discount information.",
                  "type": "array",
                  "items": {
                    "type": "object",
                    "properties": {
                      "promotionLongDesc": {
                        "description": "The description of the promotion.",
                        "type": "string"
                      },
                      "promotionName": {
                        "description": "The display name of the promotion.",
                        "type": "string"
                      },
                      "coupon": {
                        "description": "The coupon ID.",
                        "type": "string"
                      },
                      "promotionDesc": {
                        "description": "This field returns name of the promotion. Retained for backward compatibility",
                        "type": "string"
                      },
                      "promotionId": {
                        "description": "The promotion ID.",
                        "type": "string"
                      }
                    }
                  }
                },
                "detailedRecurringChargeInfo": {
                  "description": "Detailed Item Price Information.",
                  "type": "object",
                  "properties": {
                    "discounted": {
                      "description": "Whether the price is discounted.",
                      "type": "boolean"
                    },
                    "amount": {
                      "description": "The monetary amount for the recurring charge.",
                      "type": "number"
                    },
                    "quantity": {
                      "description": "The number of items covered by this recurring charge price info",
                      "type": "integer"
                    },
                    "tax": {
                      "description": "Monetary tax amount.",
                      "type": "number"
                    },
                    "orderDiscountShare": {
                      "description": "The order Discount Share.",
                      "type": "number"
                    },
                    "detailedUnitPrice": {
                      "description": "The detailed unit price: amount / quantity. (read-only)",
                      "type": "number"
                    },
                    "currencyCode": {
                      "description": "The three character currency code for the monetary amounts.",
                      "type": "string"
                    }
                  }
                },
                "activationDate": {
                  "description": "The activation date in ISO format.",
                  "type": "string"
                },
                "recurringCharge": {
                  "description": "The recurring charge for the item.",
                  "type": "number"
                }
              }
            }
          }
        }
      }
    },
    "creationTime": {
      "description": "The creation time in long seconds.",
      "type": "number"
    },
    "sourceSystem": {
      "description": "The system where the order originated.",
      "type": "string"
    },
    "dynamicProperties": {
      "description": "Read-only list of dynamic properties for the order along with meta-data.",
      "type": "array",
      "items": {
        "type": "object",
        "properties": {
          "id": {
            "description": "The ID of the dynamic property.",
            "type": "string"
          },
          "label": {
            "description": "The label of the dynamic property.",
            "type": "string"
          },
          "value": {
            "description": "The value of the dynamic property.",
            "type": "string"
          }
        }
      }
    },
    "approvalSystemMessages": {
      "description": "An array of approval messages when order going in pending approval state",
      "type": "array",
      "items": {
        "type": "string"
      }
    },
    "shippingMethod": {
      "description": "The shipping method details for the order.",
      "type": "object",
      "properties": {
        "secondaryCurrencyTaxAmount": {
          "description": "Shipping tax amount in monetry currency",
          "type": "number"
        },
        "shippingTax": {
          "description": "Shipping tax",
          "type": "number"
        },
        "cost": {
          "description": "The total cost of shipping.",
          "type": "number"
        },
        "secondaryCurrencyShipingAmount": {
          "description": "shipping amount in monetry currency ",
          "type": "number"
        },
        "value": {
          "description": "The shipping method applied to the order.",
          "type": "string"
        }
      }
    },
    "payments": {
      "description": "Payment details for the order, including additional properties specific to the payment type.",
      "type": "array",
      "items": {
        "type": "object",
        "properties": {
          "paymentGroupId": {
            "description": "Payment group ID.",
            "type": "string"
          },
          "amount": {
            "description": "Amount authorized from the payment group.",
            "type": "number"
          },
          "balance": {
            "description": "Total available balance on the gift card.",
            "type": "number"
          },
          "gatewayName": {
            "description": "Payment gateway name. e.g. chaseCreditCard.",
            "type": "string"
          },
          "giftCardNumber": {
            "description": "Gift card number.",
            "type": "string"
          },
          "paymentMethod": {
            "description": "Payment method. e.g. physicalGiftCard/ creditCard.",
            "type": "string"
          },
          "uiIntervention": {
            "description": "This decides whether the client has to do some intervention for payment. e.g. SOP.",
            "type": "string"
          },
          "isAmountRemaining": {
            "description": "A boolean to decide if more payment can be made from this payment group.",
            "type": "boolean"
          },
          "paymentState": {
            "description": "The state of the payment group. e.g. AUTHORIZED.",
            "type": "string"
          },
          "maskedCardNumber": {
            "description": "Masked gift card number.",
            "type": "string"
          }
        }
      }
    },
    "creationDate": {
      "description": "The creation date in ISO format.",
      "type": "string"
    },
    "uuid": {
      "description": "The unique ID for the order.",
      "type": "string"
    },
    "priceInfo": {
      "description": "The price information.",
      "type": "object",
      "properties": {
        "secondaryCurrencyTaxAmount": {
          "description": "The current  total tax amount in monetry currency",
          "type": "number"
        },
        "amount": {
          "description": "The total order amount.",
          "type": "number"
        },
        "total": {
          "description": "The order total.",
          "type": "number"
        },
        "secondaryCurrencyShippingAmount": {
          "description": "The current  total shipping amount in monetry currency ",
          "type": "number"
        },
        "shipping": {
          "description": "The total shipping cost.",
          "type": "number"
        },
        "primaryCurrencyTotal": {
          "description": "The current total in loyalty points in case of multi currency",
          "type": "number"
        },
        "secondaryCurrencyTotal": {
          "description": "The current  total (sum of shipping and tax)amount in monetry currency",
          "type": "number"
        },
        "secondaryCurrencyShippingSurchargeValue": {
          "description": "Extra handling costs for shipping the products in monetry currency.",
          "type": "number"
        },
        "shippingSurchargeValue": {
          "description": "Extra handling costs for shipping the products.",
          "type": "number"
        },
        "tax": {
          "description": "The total tax amount.",
          "type": "number"
        },
        "subTotal": {
          "description": "Sub-total.",
          "type": "number"
        },
        "currencyCode": {
          "description": "The currency code.",
          "type": "string"
        }
      }
    },
    "recurringChargePriceInfo": {
      "description": "Recurring charge price information.",
      "type": "object",
      "properties": {
        "amount": {
          "description": "The monetary amount of this recurring charge.",
          "type": "number"
        },
        "total": {
          "description": "The total price of the recurring charge.",
          "type": "number"
        },
        "frequencyAmountTotals": {
          "description": "The total for each recurring charge frequency",
          "type": "array",
          "items": {
            "type": "object",
            "properties": {
              "total": {
                "description": "The total amount for the frequency.",
                "type": "string"
              },
              "frequency": {
                "description": "The frequency for the item's total e.g. Monthly.",
                "type": "string"
              }
            }
          }
        },
        "shipping": {
          "description": "Cost of shipping the product.",
          "type": "number"
        },
        "tax": {
          "description": "Monetary tax amount.",
          "type": "number"
        },
        "subTotal": {
          "description": "The sub-total price of the recurring charge.",
          "type": "number"
        },
        "frequencyTaxTotals": {
          "description": "The tax for each recurring charge frequency",
          "type": "array",
          "items": {
            "type": "object",
            "properties": {
              "tax": {
                "description": "The tax amount for the frequency.",
                "type": "string"
              },
              "frequency": {
                "description": "The frequency for the item's tax e.g. Monthly.",
                "type": "string"
              }
            }
          }
        },
        "currencyCode": {
          "description": "The currency code for the monetary amounts. A three character currency code such as USD.",
          "type": "string"
        },
        "totalWithoutTax": {
          "description": "Total of recurring amount without tax included.",
          "type": "number"
        }
      }
    },
    "discountInfo": {
      "description": "The discount information.",
      "type": "object",
      "properties": {
        "orderDiscount": {
          "description": "The order discount.",
          "type": "integer"
        },
        "orderDiscountDescList": {
          "description": "The list of all the order discounts.",
          "type": "array",
          "items": {
            "type": "object",
            "properties": {
              "promotionLongDesc": {
                "description": "The description of the promotion.",
                "type": "string"
              },
              "promotionName": {
                "description": "The display name of the promotion.",
                "type": "string"
              },
              "promotionLevel": {
                "description": "The promotion level.",
                "type": "string"
              },
              "coupon": {
                "description": "The coupon code.",
                "type": "string"
              },
              "promotionDesc": {
                "description": "This field returns name of the promotion. Retained for backward compatibility",
                "type": "string"
              },
              "promotionId": {
                "description": "The promotion ID.",
                "type": "string"
              }
            }
          }
        },
        "secondaryCurrencyShippingDiscount": {
          "description": "The shipping discount in secondary currency in case of mix currency scenario",
          "type": "number"
        },
        "shippingDiscount": {
          "description": "The shipping discount.",
          "type": "integer"
        }
      }
    },
    "pricingMessages": {
      "description": "The Pricing messages information.",
      "type": "object",
      "properties": {
        "giftWithPurchaseMessages": {
          "description": "The gift with purchase messages information.",
          "type": "array",
          "items": {
            "type": "object",
            "properties": {
              "summary": {
                "description": "The pricing message summary.",
                "type": "string"
              },
              "identifier": {
                "description": "The pricing message identifier.",
                "type": "string"
              },
              "priority": {
                "description": "The pricing message priority.",
                "type": "integer"
              },
              "params": {
                "description": "The list of all message parameters.",
                "type": "array",
                "items": {
                  "type": "object",
                  "properties": {
                    "promotionId": {
                      "description": "The promotion id.",
                      "type": "string"
                    }
                  }
                }
              },
              "type": {
                "description": "The pricing message type.",
                "type": "string"
              }
            }
          }
        }
      }
    },
    "trackingInfo": {
      "description": "Tracking Information for the Order.",
      "type": "array",
      "items": {
        "type": "object",
        "properties": {
          "carrierName": {
            "description": "Carrier Name for Tracking.",
            "type": "string"
          },
          "carrierUrl": {
            "description": "Carrier URL for Tracking.",
            "type": "string"
          },
          "carrierId": {
            "description": "Carrier Id for Tracking.",
            "type": "string"
          },
          "trackingNumber": {
            "description": "Tracking Number.",
            "type": "string"
          }
        }
      }
    },
    "shoppingCart": {
      "description": "The shopping cart contents of the current order.",
      "type": "object",
      "properties": {
        "items": {
          "description": "The array of products in the shopping cart.",
          "type": "array",
          "items": {
            "type": "object",
            "properties": {
              "deactivationDate": {
                "description": "The deactivation date in ISO format.",
                "type": "string"
              },
              "dynamicProperties": {
                "description": "Array of custom properties at order line item level.",
                "type": "array",
                "items": {
                  "type": "object",
                  "properties": {
                    "id": {
                      "description": "The ID of the dynamic property.",
                      "type": "string"
                    },
                    "label": {
                      "description": "The label of the dynamic property.",
                      "type": "string"
                    },
                    "value": {
                      "description": "The value of the dynamic property.",
                      "type": "string"
                    }
                  }
                }
              },
              "externalData": {
                "description": "External data to be associated with a commerce item, provided by a configurator system.",
                "type": "array",
                "items": {
                  "type": "object",
                  "properties": {
                    "values": {
                      "description": "The array of values associated with an externalData item.",
                      "type": "object",
                      "properties": {
                        "dynamic_property_key": {
                          "description": "This property's name and value will be retrieved from a configurator system, so will be dynamically set.",
                          "type": "string"
                        }
                      }
                    },
                    "name": {
                      "description": "The name to be associated with the externalData item.",
                      "type": "string"
                    },
                    "actionCode": {
                      "description": "The action code that has been set on the externalData item by the configurator system.",
                      "type": "string"
                    }
                  }
                }
              },
              "billingAccountId": {
                "description": "The billing account ID associated to the current item.",
                "type": "string"
              },
              "childItems": {
                "description": "The array of child items in the item, if the item is a configurable item. A child item can itself contain child item array if it is a configurable product in itself.",
                "type": "array",
                "items": {
                  "type": "object",
                  "properties": {
                    "deactivationDate": {
                      "description": "The deactivation date in ISO format.",
                      "type": "string"
                    },
                    "addOnItem": {
                      "description": "Whether the child item is an add-on (externally configured) or not (externally configured).",
                      "type": "boolean"
                    },
                    "rawTotalPrice": {
                      "description": "The raw price of the product.",
                      "type": "integer"
                    },
                    "displayName": {
                      "description": "The name of the product.",
                      "type": "string"
                    },
                    "externalData": {
                      "description": "External data to be associated with a commerce item, provided by a configurator system.",
                      "type": "array",
                      "items": {
                        "type": "object",
                        "properties": {
                          "values": {
                            "description": "The array of values associated with an externalData item.",
                            "type": "object",
                            "properties": {
                              "dynamic_property_key": {
                                "description": "This property's name and value will be retrieved from a configurator system, so will be dynamically set.",
                                "type": "string"
                              }
                            }
                          },
                          "name": {
                            "description": "The name to be associated with the externalData item.",
                            "type": "string"
                          },
                          "actionCode": {
                            "description": "The action code that has been set on the externalData item by the configurator system.",
                            "type": "string"
                          }
                        }
                      }
                    },
                    "billingAccountId": {
                      "description": "The billing account ID associated to the current item.",
                      "type": "string"
                    },
                    "externalPrice": {
                      "description": "A price for a quantity of 1 of this line item which will be used in place of the standard catalog price (this price will be verified to ensure it is allowable).",
                      "type": "number"
                    },
                    "assetId": {
                      "description": "The asset ID corresponding to the current item.",
                      "type": "string"
                    },
                    "actionCode": {
                      "description": "The action code that has been set on the item by the configurator system.",
                      "type": "string"
                    },
                    "id": {
                      "description": "Repository id of the commerce item.",
                      "type": "string"
                    },
                    "serviceId": {
                      "description": "The service ID associated to the current item.",
                      "type": "string"
                    },
                    "unitPrice": {
                      "description": "The unit price of the product.",
                      "type": "integer"
                    },
                    "serviceAccountId": {
                      "description": "The service account ID associated to the current item.",
                      "type": "string"
                    },
                    "configurationOptionId": {
                      "description": "ID of the catalog's configurationOption associated with this item.",
                      "type": "string"
                    },
                    "amount": {
                      "description": "The total amount of this item including its child items amounts.",
                      "type": "integer"
                    },
                    "quantity": {
                      "description": "The quantity of the product.",
                      "type": "integer"
                    },
                    "productId": {
                      "description": "ID of the product in the cart.",
                      "type": "string"
                    },
                    "externalRecurringCharge": {
                      "description": "The external recurring price.",
                      "type": "number"
                    },
                    "externalPriceQuantity": {
                      "description": "The maximum quantity of this line item which may be purchased at the external price (this quantity will be verified to ensure it is allowable).",
                      "type": "integer"
                    },
                    "externalRecurringChargeFrequency": {
                      "description": "The frequency for the recurring charge e.g. Monthly.",
                      "type": "string"
                    },
                    "configurablePropertyId": {
                      "description": "ID of the catalog's configurableProperty associated with this item.",
                      "type": "string"
                    },
                    "catRefId": {
                      "description": "skuid of the item.",
                      "type": "string"
                    },
                    "externalRecurringChargeDuration": {
                      "description": "The duration for the recurring charge e.g. 12 months.",
                      "type": "string"
                    },
                    "customerAccountId": {
                      "description": "The customer account ID associated to the current item.",
                      "type": "string"
                    },
                    "detailedRecurringChargeInfo": {
                      "description": "Detailed Item Price Information.",
                      "type": "object",
                      "properties": {
                        "discounted": {
                          "description": "Whether the price is discounted.",
                          "type": "boolean"
                        },
                        "amount": {
                          "description": "The monetary amount for the recurring charge.",
                          "type": "number"
                        },
                        "quantity": {
                          "description": "The number of items covered by this recurring charge price info",
                          "type": "integer"
                        },
                        "tax": {
                          "description": "Monetary tax amount.",
                          "type": "number"
                        },
                        "orderDiscountShare": {
                          "description": "The order Discount Share.",
                          "type": "number"
                        },
                        "detailedUnitPrice": {
                          "description": "The detailed unit price: amount / quantity. (read-only)",
                          "type": "number"
                        },
                        "currencyCode": {
                          "description": "The three character currency code for the monetary amounts.",
                          "type": "string"
                        }
                      }
                    },
                    "shopperInput": {
                      "description": "Map of shopper input keys to values",
                      "additionalProperties": {
                        "type": "string"
                      },
                      "type": "object"
                    },
                    "activationDate": {
                      "description": "The activation date in ISO format.",
                      "type": "string"
                    },
                    "recurringCharge": {
                      "description": "The recurring charge for the item.",
                      "type": "number"
                    }
                  }
                }
              },
              "externalPrice": {
                "description": "A price for a quantity of 1 of this line item which will be used in place of the standard catalog price (this price will be verified to ensure it is allowable).",
                "type": "number"
              },
              "commerceItemId": {
                "description": "The unique line item ID distinguisher.",
                "type": "string"
              },
              "assetId": {
                "description": "The asset ID corresponding to the current item.",
                "type": "string"
              },
              "price": {
                "description": "The actual price of the product.",
                "type": "integer"
              },
              "variant": {
                "description": "List of variants for the product.",
                "type": "array",
                "items": {
                  "type": "object",
                  "properties": {
                    "optionValue": {
                      "description": "The variant option value.",
                      "type": "string"
                    },
                    "optionName": {
                      "description": "The variant option name.",
                      "type": "string"
                    }
                  }
                }
              },
              "actionCode": {
                "description": "The action code that has been set on the item by the configurator system.",
                "type": "string"
              },
              "id": {
                "description": "Repository id of the commerce item.",
                "type": "string"
              },
              "serviceId": {
                "description": "The service ID associated to the current item.",
                "type": "string"
              },
              "unitPrice": {
                "description": "The unit price of the product.",
                "type": "integer"
              },
              "serviceAccountId": {
                "description": "The service account ID associated to the current item.",
                "type": "string"
              },
              "quantity": {
                "description": "The quantity of the product.",
                "type": "integer"
              },
              "productId": {
                "description": "ID of the product in the cart.",
                "type": "string"
              },
              "externalRecurringCharge": {
                "description": "The external recurring price.",
                "type": "number"
              },
              "giftWithPurchaseCommerceItemMarkers": {
                "description": "The array of giftWithPurchaseCommerceItemMarkers.",
                "type": "array",
                "items": {
                  "type": "object",
                  "properties": {
                    "remainingQuantity": {
                      "description": "The quantity of the commerce item that is not affected by gift with purchase.",
                      "type": "number"
                    },
                    "selectedQuantity": {
                      "description": "The quantity of the free gift that this commerce item is making free and was selected by the shopper.",
                      "type": "number"
                    },
                    "data": {
                      "description": "The gift hash code for this gift with purchase promotion.",
                      "type": "integer"
                    },
                    "automaticQuantity": {
                      "description": "The quantity of the free gift that this commerce item is making free and was auto added by pricing.",
                      "type": "number"
                    },
                    "value": {
                      "description": "The gift with purchase promotion id.",
                      "type": "string"
                    },
                    "targetedQuantity": {
                      "description": "The quantity of the free gift that this commerce item is making free and was targeted by pricing.",
                      "type": "number"
                    },
                    "key": {
                      "description": "atg.gwp",
                      "type": "string"
                    }
                  }
                }
              },
              "externalPriceQuantity": {
                "description": "The maximum quantity of this line item which may be purchased at the external price (this quantity will be verified to ensure it is allowable).",
                "type": "integer"
              },
              "externalRecurringChargeFrequency": {
                "description": "The frequency for the recurring charge e.g. Monthly.",
                "type": "string"
              },
              "externalRecurringChargeDuration": {
                "description": "The duration for the recurring charge e.g. 12 months.",
                "type": "string"
              },
              "catRefId": {
                "description": "The category to which the product belongs.",
                "type": "string"
              },
              "skuProperties": {
                "description": "Sku properties Information",
                "type": "array",
                "items": {
                  "type": "object",
                  "properties": {
                    "propertyType": {
                      "description": "Type that indicates whether it is a base or a custom SKU property,",
                      "type": "string"
                    },
                    "name": {
                      "description": "Name of the Dynamic SKU Property.",
                      "type": "string"
                    },
                    "id": {
                      "description": "ID of the Dynamic SKU Property.",
                      "type": "string"
                    },
                    "value": {
                      "description": "Value of the Dynamic SKU Property.",
                      "type": "string"
                    }
                  }
                }
              },
              "customerAccountId": {
                "description": "The customer account ID associated to the current item.",
                "type": "string"
              },
              "discountInfo": {
                "description": "The discount information.",
                "type": "array",
                "items": {
                  "type": "object",
                  "properties": {
                    "promotionLongDesc": {
                      "description": "The description of the promotion.",
                      "type": "string"
                    },
                    "promotionName": {
                      "description": "The display name of the promotion.",
                      "type": "string"
                    },
                    "promotionLevel": {
                      "description": "The promotion level.",
                      "type": "string"
                    },
                    "coupon": {
                      "description": "The coupon ID.",
                      "type": "string"
                    },
                    "totalAdjustment": {
                      "description": "Total adjustment by the promotion.",
                      "type": "number"
                    },
                    "promotionDesc": {
                      "description": "This field returns name of the promotion. Retained for backward compatibility",
                      "type": "string"
                    },
                    "promotionId": {
                      "description": "The promotion ID.",
                      "type": "string"
                    },
                    "giftWithPurchaseDiscountInfo": {
                      "description": "The gift information.",
                      "type": "array",
                      "items": {
                        "type": "object",
                        "properties": {
                          "giftWithPurchaseChoicesAvailable": {
                            "description": "If this gift with purchase has multiple gift choices.",
                            "type": "boolean"
                          },
                          "giftWithPurchaseQuantity": {
                            "description": "The quantity that is gift quantity",
                            "type": "number"
                          },
                          "giftWithPurchaseIdentifier": {
                            "description": "The gift hash code for this gift with purchase promotion.",
                            "type": "integer"
                          }
                        }
                      }
                    }
                  }
                }
              },
              "detailedRecurringChargeInfo": {
                "description": "Detailed Item Price Information.",
                "type": "object",
                "properties": {
                  "discounted": {
                    "description": "Whether the price is discounted.",
                    "type": "boolean"
                  },
                  "amount": {
                    "description": "The monetary amount for the recurring charge.",
                    "type": "number"
                  },
                  "quantity": {
                    "description": "The number of items covered by this recurring charge price info",
                    "type": "integer"
                  },
                  "tax": {
                    "description": "Monetary tax amount.",
                    "type": "number"
                  },
                  "orderDiscountShare": {
                    "description": "The order Discount Share.",
                    "type": "number"
                  },
                  "detailedUnitPrice": {
                    "description": "The detailed unit price: amount / quantity. (read-only)",
                    "type": "number"
                  },
                  "currencyCode": {
                    "description": "The three character currency code for the monetary amounts.",
                    "type": "string"
                  }
                }
              },
              "shopperInput": {
                "description": "Map of shopper input keys to values",
                "additionalProperties": {
                  "type": "string"
                },
                "type": "object"
              },
              "activationDate": {
                "description": "The activation date in ISO format.",
                "type": "string"
              },
              "recurringCharge": {
                "description": "The recurring charge for the item.",
                "type": "number"
              }
            }
          }
        }
      }
    },
    "giftWithPurchaseInfo": {
      "description": "The gift information.",
      "type": "array",
      "items": {
        "type": "object",
        "properties": {
          "giftWithPurchaseQuantityAvailableForSelection": {
            "description": "gift quantity available for selection",
            "type": "number"
          },
          "giftWithPurchaseType": {
            "description": "The type of the gift. (sku, product)",
            "type": "string"
          },
          "giftWithPurchaseDetail": {
            "description": "String identifying the free gift, usually the repository id of the gift type.",
            "type": "string"
          },
          "promotionId": {
            "description": "The gift with purchase promotion id",
            "type": "string"
          },
          "giftWithPurchaseIdentifier": {
            "description": "An identifier used to track which gift selection in the promotion this is.  It allows the commerce item marker to link to this one.",
            "type": "integer"
          }
        }
      }
    },
    "shippingAddress": {
      "description": "The shipping address details.",
      "type": "object",
      "properties": {
        "lastName": {
          "description": "Last name.",
          "type": "string"
        },
        "country": {
          "description": "Country.",
          "type": "string"
        },
        "address3": {
          "description": "Address snippet.",
          "type": "string"
        },
        "address2": {
          "description": "Address snippet.",
          "type": "string"
        },
        "city": {
          "description": "City.",
          "type": "string"
        },
        "prefix": {
          "description": "Name prefix.",
          "type": "string"
        },
        "address1": {
          "description": "Address snippet.",
          "type": "string"
        },
        "postalCode": {
          "description": "Postal code.",
          "type": "string"
        },
        "jobTitle": {
          "description": "Job title.",
          "type": "string"
        },
        "companyName": {
          "description": "Company name.",
          "type": "string"
        },
        "county": {
          "description": "County.",
          "type": "string"
        },
        "suffix": {
          "description": "Name suffix.",
          "type": "string"
        },
        "selectedCountry": {
          "description": "Country code.",
          "type": "string"
        },
        "firstName": {
          "description": "First name",
          "type": "string"
        },
        "phoneNumber": {
          "description": "Phone number.",
          "type": "string"
        },
        "faxNumber": {
          "description": "Fax number.",
          "type": "string"
        },
        "alias": {
          "description": "Address alias.",
          "type": "string"
        },
        "middleName": {
          "description": "Middle name.",
          "type": "string"
        },
        "state": {
          "description": "State.",
          "type": "string"
        },
        "selectedState": {
          "description": "State code.",
          "type": "string"
        },
        "email": {
          "description": "Email address.",
          "type": "string"
        },
        "state_ISOCode": {
          "description": "State ISO code.",
          "type": "string"
        }
      }
    },
    "id": {
      "description": "The order ID.",
      "type": "string"
    },
    "quoteInfo": {
      "description": "the quote information of the order",
      "type": "object",
      "properties": {
        "providerNote": {
          "description": "the provider note for the quoted order",
          "type": "string"
        },
        "notes": {
          "description": "the notes (history) for the order",
          "type": "array",
          "items": {
            "type": "object",
            "properties": {
              "requestDate/quoteDate/rejectionDate": {
                "description": "the request/quote/rejection date for the note",
                "type": "number"
              },
              "profileType": {
                "description": "the profile type of the user that requested the quote",
                "type": "string"
              },
              "profileId": {
                "description": "the profile id of the user",
                "type": "string"
              },
              "requesterNote/providerNote/rejectionNote": {
                "description": "the requester/provider/rejection note",
                "type": "string"
              }
            }
          }
        },
        "rejectionDate": {
          "description": "rejection date of the quoted order",
          "type": "string"
        },
        "requestDate": {
          "description": "the date when the quote was requested in ISO format",
          "type": "string"
        },
        "errorInfo": {
          "description": "the array of errors, if any",
          "type": "array",
          "items": {
            "type": "string"
          }
        },
        "externalId": {
          "description": "the external id for the quote",
          "type": "string"
        },
        "rejectionNote": {
          "description": "the rejection note for an order whose quote has been rejected by user",
          "type": "string"
        },
        "quoteDate": {
          "description": "the date the order was quoted in milliseconds",
          "type": "number"
        },
        "expirationDate": {
          "description": "the expiration date of the quoted order, if any",
          "type": "string"
        }
      }
    },
    "giftWithPurchaseOrderMarkers": {
      "description": "giftWithPurchaseOrderMarker information",
      "type": "array",
      "items": {
        "type": "object",
        "properties": {
          "quantity": {
            "description": "The total quantity of sku for this gift selection.",
            "type": "number"
          },
          "selectedQuantity": {
            "description": "The quantity of free sku for this gift selection that has already been selected by the Shopper and added to the order.",
            "type": "integer"
          },
          "removedQuantity": {
            "description": "The amount of free quantity that has since been manually removed by a Shopper.",
            "type": "number"
          },
          "data": {
            "description": "An identifier used to track which gift selection in the promotion this is.  It allows the commerce item marker to link to this one.",
            "type": "integer"
          },
          "autoRemove": {
            "description": "Flag to indicate whether free gifts should be auto removed if the promotion no longer qualifies.",
            "type": "boolean"
          },
          "giftDetail": {
            "description": "String identifying the free gift, usually the repository id of the gift type.",
            "type": "string"
          },
          "automaticQuantity": {
            "description": "The quantity of free sku for this gift selection that has already been auto added to the order.",
            "type": "number"
          },
          "giftType": {
            "description": "The type of the gift. (sku, product)",
            "type": "string"
          },
          "failedQuantity": {
            "description": "The amount of automatic free quantity that failed to be added to the cart due to some pricing error, e.g. invalid site.",
            "type": "number"
          },
          "value": {
            "description": "The gift with purchase promotion id",
            "type": "string"
          },
          "targetedQuantity": {
            "description": "The quantity of free sku for this gift selection that has already been targeted and made free by the calculator in the order.",
            "type": "number"
          },
          "key": {
            "description": "atg.gwp",
            "type": "string"
          }
        }
      }
    }
  }
}